wise/__init__.py
wise/features.py
wise/jsonpickle_numpy.py
wise/matcher.py
wise/project.py
wise/scc.py
wise/tasks.py
wise/wds.py
wise/wiseutils.py
wise/actions/__init__.py
wise/actions/actions.py
wise/actions/wise_detect.py
wise/actions/wise_info.py
wise/actions/wise_match.py
wise/actions/wise_plot_features.py
wise/actions/wise_plot_sep_from_core.py
wise/actions/wise_region.py
wise/actions/wise_select_files.py
wise/actions/wise_settings.py
wise/actions/wise_stack.py
wise/actions/wise_view.py
wise/actions/wise_view_features.py
wise/actions/wise_view_links.py
wisetool-0.4.7.data/scripts/wise
wisetool-0.4.7.dist-info/LICENSE
wisetool-0.4.7.dist-info/METADATA
wisetool-0.4.7.dist-info/WHEEL
wisetool-0.4.7.dist-info/top_level.txt
wisetool-0.4.7.dist-info/RECORD
